dayamlchecker/__init__.py
dayamlchecker/__main__.py
dayamlchecker/yaml_structure.py
dayamlchecker-0.1.0.dist-info/licenses/LICENSE
dayamlchecker-0.1.0.dist-info/METADATA
dayamlchecker-0.1.0.dist-info/WHEEL
dayamlchecker-0.1.0.dist-info/top_level.txt
dayamlchecker-0.1.0.dist-info/RECORD
