Metadata-Version: 2.4
Name: dayamlchecker
Version: 0.1.0
Summary: An LSP for Docassemble YAML interviews
Author-email: Bryce Willey <bryce.steven.willey@gmail.com>
License-Expression: MIT
Requires-Python: >=3.12
License-File: LICENSE
Requires-Dist: mako>=1.3.10
Requires-Dist: pyyaml>=6.0.2
Dynamic: license-file
